LICENSE
README.md
pyproject.toml
setup.cfg
setup.py
data/params_brain_sim_1_5T.csv
llckbdm/__init__.py
llckbdm/kbdm.py
llckbdm/llckbdm.py
llckbdm/metrics.py
llckbdm/min_rmse_kbdm.py
llckbdm/sampling.py
llckbdm/sig_gen.py
llckbdm.egg-info/PKG-INFO
llckbdm.egg-info/SOURCES.txt
llckbdm.egg-info/dependency_links.txt
llckbdm.egg-info/requires.txt
llckbdm.egg-info/top_level.txt
llckbdm/_tests/__init__.py
llckbdm/_tests/fixtures.py
llckbdm/_tests/test_kbdm.py
llckbdm/_tests/test_llckbdm.py
llckbdm/_tests/test_metrics.py
llckbdm/_tests/test_min_rmse_kbdm.py
llckbdm/_tests/test_sampling.py
llckbdm/_tests/test_sig_gen.py