Metadata-Version: 2.1
Name: llckbdm
Version: 0.2.3
Summary: Line List Clustering Krylov Basis Diagonalization Method implementation in Python
Home-page: https://github.com/danilomendesdias/llckbdm
Author: Danilo Mendes Dias Delfino da Silva
Author-email: danilomendesdias@gmail.com
License: MIT
Project-URL: Source, https://github.com/danilomendesdias/llckbdm
Keywords: kbdm mrs fitting hip llckbdm nmr
Platform: UNKNOWN
Classifier: Development Status :: 3 - Alpha
Classifier: Intended Audience :: Science/Research
Classifier: Topic :: Scientific/Engineering :: Medical Science Apps.
Classifier: Topic :: Scientific/Engineering :: Physics
Classifier: License :: OSI Approved :: MIT License
Classifier: Programming Language :: Python :: 3.6
Classifier: Programming Language :: Python :: 3.7
Classifier: Programming Language :: Python :: 3.8
Requires-Python: >=3.6
